xrfit/__init__.py
xrfit/arr.py
xrfit/assess.py
xrfit/base.py
xrfit/display.py
xrfit/fit.py
xrfit/params.py
xrfit-0.7.0.dist-info/METADATA
xrfit-0.7.0.dist-info/WHEEL
xrfit-0.7.0.dist-info/licenses/LICENSE
xrfit-0.7.0.dist-info/RECORD
