Metadata-Version: 2.4
Name: xrfit
Version: 0.7.0
Summary: xrfit
Project-URL: Repository, https://github.com/mgjho/xrfit.git
Project-URL: Issues, https://github.com/mgjho/xrfit/issues
Author-email: Mingi Jho <mingi.jho@kaist.ac.kr>
License:                     GNU GENERAL PUBLIC LICENSE
License-File: LICENSE
Keywords: Data Analysis,Fitting
Classifier: Development Status :: 4 - Beta
Classifier: Intended Audience :: Science/Research
Classifier: License :: OSI Approved :: GNU General Public License v3 or later (GPLv3+)
Classifier: Operating System :: OS Independent
Classifier: Programming Language :: Python :: 3.11
Classifier: Programming Language :: Python :: 3.12
Classifier: Programming Language :: Python :: 3.13
Classifier: Topic :: Scientific/Engineering
Requires-Python: >=3.11
Requires-Dist: lmfit>=1.3.2
Requires-Dist: lxml>=5.3.0
Requires-Dist: numpy>=1.3.2
Requires-Dist: pyqt6>=6.8.0
Requires-Dist: pyqtgraph>=0.13.7
Requires-Dist: pytest>=8.3.4
Requires-Dist: qtpy>=2.4.2
Requires-Dist: scipy>=1.15.1
Requires-Dist: xarray>=2025.1.2
